paddypy/__init__.py
paddypy/access.py
paddypy/log.py
paddypy-0.2.6.dist-info/LICENSE
paddypy-0.2.6.dist-info/METADATA
paddypy-0.2.6.dist-info/WHEEL
paddypy-0.2.6.dist-info/top_level.txt
paddypy-0.2.6.dist-info/RECORD
