Metadata-Version: 2.1
Name: paddypy
Version: 0.2.6
Summary: Collection of helpfull extensions
Author: Patrik
Author-email: <patrikhartl@gmail.com>
Keywords: python,appconfiguration,azure
Classifier: Development Status :: 1 - Planning
Classifier: Intended Audience :: Developers
Classifier: Programming Language :: Python :: 3
Classifier: Programming Language :: Python :: 3.6
Classifier: Programming Language :: Python :: 3.7
Classifier: Programming Language :: Python :: 3.8
Classifier: Programming Language :: Python :: 3.9
Classifier: Programming Language :: Python :: 3.10
Classifier: Programming Language :: Python :: 3.11
Classifier: Operating System :: Microsoft :: Windows
Classifier: Operating System :: POSIX
Classifier: Environment :: Web Environment
License-File: LICENSE
Requires-Dist: azure-appconfiguration (>=1.1.1)
Requires-Dist: texttable (>=1.4.4)
Requires-Dist: azure-identity (>=1.5.0)
Requires-Dist: azure-keyvault-secrets (>=4.1.0)
Requires-Dist: opencensus-ext-azure (>=1.1.9)
